minimal/__init__.py
minimal/_version.py
minimal/minimal.py
minimal_deploy-0.1.1.dist-info/METADATA
minimal_deploy-0.1.1.dist-info/WHEEL
minimal_deploy-0.1.1.dist-info/top_level.txt
minimal_deploy-0.1.1.dist-info/RECORD
