Metadata-Version: 2.1
Name: minimal-deploy
Version: 0.1.1
Summary: A minimal Python package
Home-page: https://github.com/tlambert03/minimal-deploy
Author: Talley
Author-email: talley.lambert@gmail.com
License: UNKNOWN
Platform: UNKNOWN
